TrafficLightFSM/fsm_trafficlight.v
module fsm_trafficlight #(
    parameter WIDTH = 5
)(
    input wire clk,
    input wire rst_n,
    input wire en,
    input wire last_light,
    output reg [1:0] state,
    output reg [WIDTH-1:0] time_light
);

    // State encoding
    localparam IDLE   = 2'b00;
    localparam RED    = 2'b01;
    localparam GREEN  = 2'b10;
    localparam YELLOW = 2'b11;

    // Time settings for each state
    localparam TIME_RED    = 5'd18;
    localparam TIME_GREEN  = 5'd15;
    localparam TIME_YELLOW = 5'd3;

    // Next state and output logic
    reg [1:0] next_state;
    reg [WIDTH-1:0] next_time;

    // Combinational logic for next state
    always @(*) begin
        // Giá trị mặc định - giữ trạng thái hiện tại
        next_state = state;
        next_time = time_light;

        if (en && last_light) begin
            case (state)
                IDLE: begin
                    next_state = RED;
                    next_time = TIME_RED;
                end
                RED: begin
                    next_state = GREEN;
                    next_time = TIME_GREEN;
                end
                GREEN: begin
                    next_state = YELLOW;
                    next_time = TIME_YELLOW;
                end
                YELLOW: begin
                    next_state = RED;
                    next_time = TIME_RED;
                end
            endcase
        end
    end

    // Sequential logic for state update
    always @(posedge clk or negedge rst_n) begin
        if (!rst_n) begin
            state <= IDLE;
            time_light <= TIME_RED;
        end 
        else begin
            state <= next_state;
            time_light <= next_time;
        end
    end

endmodule


`timescale 1ns/1ps

module fsm_trafficlight_tb();
    // Parameters
    parameter WIDTH = 5;
    parameter CLK_PERIOD = 10;  // 10ns clock period

    // Test signals
    reg clk;
    reg rst_n;
    reg en;
    reg last_light;
    wire [1:0] state;
    wire [WIDTH-1:0] time_light;

    // Instantiate DUT
    fsm_trafficlight #(
        .WIDTH(WIDTH)
    ) dut (
        .clk(clk),
        .rst_n(rst_n),
        .en(en),
        .last_light(last_light),
        .state(state),
        .time_light(time_light)
    );

    // Clock generation
    initial begin
        clk = 0;
        forever #(CLK_PERIOD/2) clk = ~clk;
    end

    // Test stimulus
    initial begin
        // Setup waveform dumping
        $dumpfile("fsm_trafficlight.vcd");
        $dumpvars(0, fsm_trafficlight_tb);

        // Test 1: Reset
        rst_n = 0;
        en = 0;
        last_light = 0;
        #(CLK_PERIOD*2);
        
        // Test 2: Enable but no last_light
        rst_n = 1;
        en = 1;
        last_light = 0;
        #(CLK_PERIOD*2);
        
        // Test 3: Complete state transition sequence
        // IDLE -> RED -> GREEN -> YELLOW -> RED
        
        // IDLE to RED
        last_light = 1;
        #(CLK_PERIOD);
        last_light = 0;
        #(CLK_PERIOD*2);
        
        // RED to GREEN
        last_light = 1;
        #(CLK_PERIOD);
        last_light = 0;
        #(CLK_PERIOD*2);
        
        // GREEN to YELLOW
        last_light = 1;
        #(CLK_PERIOD);
        last_light = 0;
        #(CLK_PERIOD*2);
        
        // YELLOW to RED
        last_light = 1;
        #(CLK_PERIOD);
        last_light = 0;
        #(CLK_PERIOD*2);
        
        // Test 4: Disable while in state
        en = 0;
        #(CLK_PERIOD*2);
        last_light = 1;
        #(CLK_PERIOD*2);
        
        // End simulation
        #(CLK_PERIOD*2);
        $finish;
    end

    // Monitor state changes
    initial begin
        $monitor("Time=%0t rst_n=%0b en=%0b last_light=%0b state=%0b time_light=%0d",
                 $time, rst_n, en, last_light, state, time_light);
    end

    // Assertions
    always @(posedge clk) begin
        // Check reset state
        if (!rst_n && (state !== 2'b00))
            $display("Error: Invalid reset state at time %0t", $time);
            
        // Check time_light values
        case (state)
            2'b00: // IDLE
                if (time_light !== 5'd18)
                    $display("Error: Invalid IDLE time at time %0t", $time);
            2'b01: // RED
                if (time_light !== 5'd18)
                    $display("Error: Invalid RED time at time %0t", $time);
            2'b10: // GREEN
                if (time_light !== 5'd15)
                    $display("Error: Invalid GREEN time at time %0t", $time);
            2'b11: // YELLOW
                if (time_light !== 5'd3)
                    $display("Error: Invalid YELLOW time at time %0t", $time);
        endcase
    end

endmodule

TrafficLightFSM/fsm_trafficlight.vcd
$date
	Mon Aug 11 14:18:00 2025
$end
$version
	Icarus Verilog
$end
$timescale
	1ps
$end
$scope module fsm_trafficlight_tb $end
$var wire 5 ! time_light [4:0] $end
$var wire 2 " state [1:0] $end
$var parameter 32 # CLK_PERIOD $end
$var parameter 32 $ WIDTH $end
$var reg 1 % clk $end
$var reg 1 & en $end
$var reg 1 ' last_light $end
$var reg 1 ( rst_n $end
$scope module dut $end
$var wire 1 % clk $end
$var wire 1 & en $end
$var wire 1 ' last_light $end
$var wire 1 ( rst_n $end
$var parameter 2 ) GREEN $end
$var parameter 2 * IDLE $end
$var parameter 2 + RED $end
$var parameter 5 , TIME_GREEN $end
$var parameter 5 - TIME_RED $end
$var parameter 5 . TIME_YELLOW $end
$var parameter 32 / WIDTH $end
$var parameter 2 0 YELLOW $end
$var reg 2 1 next_state [1:0] $end
$var reg 5 2 next_time [4:0] $end
$var reg 2 3 state [1:0] $end
$var reg 5 4 time_light [4:0] $end
$upscope $end
$upscope $end
$enddefinitions $end
$comment Show the parameter values. $end
$dumpall
b11 0
b101 /
b11 .
b10010 -
b1111 ,
b1 +
b0 *
b10 )
b101 $
b1010 #
$end
#0
$dumpvars
b10010 4
b0 3
b10010 2
b0 1
0(
0'
0&
0%
b0 "
b10010 !
$end
#5000
1%
#10000
0%
#15000
1%
#20000
0%
1&
1(
#25000
1%
#30000
0%
#35000
1%
#40000
b1 1
0%
1'
#45000
b1111 2
b10 1
b1 "
b1 3
1%
#50000
b10010 2
b1 1
0%
0'
#55000
1%
#60000
0%
#65000
1%
#70000
b1111 2
b10 1
0%
1'
#75000
b11 2
b11 1
b1111 !
b1111 4
b10 "
b10 3
1%
#80000
b1111 2
b10 1
0%
0'
#85000
1%
#90000
0%
#95000
1%
#100000
b11 2
b11 1
0%
1'
#105000
b10010 2
b1 1
b11 !
b11 4
b11 "
b11 3
1%
#110000
b11 2
b11 1
0%
0'
#115000
1%
#120000
0%
#125000
1%
#130000
b10010 2
b1 1
0%
1'
#135000
b1111 2
b10 1
b10010 !
b10010 4
b1 "
b1 3
1%
#140000
b10010 2
b1 1
0%
0'
#145000
1%
#150000
0%
#155000
1%
#160000
0%
0&
#165000
1%
#170000
0%
#175000
1%
#180000
0%
1'
