Counter/counter.v
module counter #(
    parameter pGREEN_INIT_VAL = 14,
    parameter pYELLOW_INIT_VAL = 2,
    parameter pRED_INIT_VAL = 17,
    parameter pCNT_WIDTH = 5,
    parameter pINIT_WIDTH = 3
)(
    input wire clk,
    input wire rst_n,
    input wire en,
    input wire [pINIT_WIDTH-1:0] init,
    output wire last,
    output wire [pCNT_WIDTH-1:0] count_out
);

    localparam pGREEN_IDX = 0;
    localparam pYELLOW_IDX = 1;
    localparam pRED_IDX = 2;

    reg [pCNT_WIDTH-1:0] count;
    wire [pCNT_WIDTH-1:0] next_count;
    wire [pCNT_WIDTH-1:0] dec_value;

    // Check if count is zero
    wire count_is_zero = (count == {pCNT_WIDTH{1'b0}});

    // Decrement only if count is not zero
    assign dec_value = count_is_zero ? count : count + 5'b11111;

    // Next count logic
    assign next_count = !rst_n              ? pGREEN_INIT_VAL :
                       init[pGREEN_IDX]     ? pGREEN_INIT_VAL :
                       init[pYELLOW_IDX]    ? pYELLOW_INIT_VAL :
                       init[pRED_IDX]       ? pRED_INIT_VAL : 
                       en                   ? dec_value : count;

    // Counter register
    always @(posedge clk or negedge rst_n) begin
        if(!rst_n) begin
            count <= pGREEN_INIT_VAL;  // Reset to GREEN value
        end else if (en) begin 
            count <= next_count;
        end else begin
            count <= count;  // Hold value when not enabled
        end
    end

    // Output logic
    assign last = count_is_zero;
    assign count_out = count;

endmodule

// Testbench
`timescale 1ns/1ps
module counter_tb;
    // Parameters
    parameter pGREEN_INIT_VAL  = 14;
    parameter pYELLOW_INIT_VAL = 2;
    parameter pRED_INIT_VAL    = 17;
    parameter pCNT_WIDTH       = 5;
    parameter pINIT_WIDTH      = 3;
    parameter CLK_PERIOD       = 10;

    // Signals
    reg clk;
    reg rst_n;
    reg en;
    reg [pINIT_WIDTH-1:0] init;
    wire last;
    wire [pCNT_WIDTH-1:0] count_out;

    // Instantiate DUT
    counter #(
        .pGREEN_INIT_VAL(pGREEN_INIT_VAL),
        .pYELLOW_INIT_VAL(pYELLOW_INIT_VAL),
        .pRED_INIT_VAL(pRED_INIT_VAL),
        .pCNT_WIDTH(pCNT_WIDTH),
        .pINIT_WIDTH(pINIT_WIDTH)
    ) uut (
        .clk(clk),
        .rst_n(rst_n),
        .en(en),
        .init(init),
        .last(last),
        .count_out(count_out)
    );

    // Clock generation
    initial begin
        clk = 0;
        forever #(CLK_PERIOD/2) clk = ~clk;
    end

    // Monitor
    initial begin
        $monitor("Time=%0t rst_n=%b en=%b init=%b count=%d last=%b",
                 $time, rst_n, en, init, count_out, last);
    end

    initial begin
        $dumpfile("counter_tb.vcd");
        $dumpvars(0, counter_tb);
    end

    // Test sequence
    initial begin
        // Initialize
        rst_n = 0;
        en = 0;
        init = 3'b000;
        #20;

        // Test GREEN
        rst_n = 1;
        en = 1;
        init = 3'b001;
        #10;
        init = 3'b000;
        repeat(14) @(posedge clk);

        // Test YELLOW
        init = 3'b010;
        #10;
        init = 3'b000;
        repeat(2) @(posedge clk);

        // Test RED
        init = 3'b100;
        #10;
        init = 3'b000;
        repeat(17) @(posedge clk);

        // Test disable
        en = 0;
        #20;

        $finish;
    end

endmodule

Counter/counter_tb.vcd
$date
	Wed Aug 13 22:52:04 2025
$end
$version
	Icarus Verilog
$end
$timescale
	1ps
$end
$scope module counter_tb $end
$var wire 1 ! last $end
$var wire 5 " count_out [4:0] $end
$var parameter 32 # CLK_PERIOD $end
$var parameter 32 $ pCNT_WIDTH $end
$var parameter 32 % pGREEN_INIT_VAL $end
$var parameter 32 & pINIT_WIDTH $end
$var parameter 32 ' pRED_INIT_VAL $end
$var parameter 32 ( pYELLOW_INIT_VAL $end
$var reg 1 ) clk $end
$var reg 1 * en $end
$var reg 3 + init [2:0] $end
$var reg 1 , rst_n $end
$scope module uut $end
$var wire 1 ) clk $end
$var wire 5 - count_out [4:0] $end
$var wire 1 * en $end
$var wire 3 . init [2:0] $end
$var wire 1 ! last $end
$var wire 1 , rst_n $end
$var wire 5 / next_count [4:0] $end
$var wire 5 0 dec_value [4:0] $end
$var wire 1 1 count_is_zero $end
$var parameter 32 2 pCNT_WIDTH $end
$var parameter 32 3 pGREEN_IDX $end
$var parameter 32 4 pGREEN_INIT_VAL $end
$var parameter 32 5 pINIT_WIDTH $end
$var parameter 32 6 pRED_IDX $end
$var parameter 32 7 pRED_INIT_VAL $end
$var parameter 32 8 pYELLOW_IDX $end
$var parameter 32 9 pYELLOW_INIT_VAL $end
$var reg 5 : count [4:0] $end
$upscope $end
$upscope $end
$enddefinitions $end
$comment Show the parameter values. $end
$dumpall
b10 9
b1 8
b10001 7
b10 6
b11 5
b1110 4
b0 3
b101 2
b10 (
b10001 '
b11 &
b1110 %
b101 $
b1010 #
$end
#0
$dumpvars
b1110 :
01
b1101 0
b1110 /
b0 .
b1110 -
0,
b0 +
0*
0)
b1110 "
0!
$end
#5000
1)
#10000
0)
#15000
1)
#20000
0)
b1 +
b1 .
1*
1,
#25000
1)
#30000
b1101 /
0)
b0 +
b0 .
#35000
b1100 /
b1100 0
b1101 "
b1101 -
b1101 :
1)
#40000
0)
#45000
b1011 /
b1011 0
b1100 "
b1100 -
b1100 :
1)
#50000
0)
#55000
b1010 /
b1010 0
b1011 "
b1011 -
b1011 :
1)
#60000
0)
#65000
b1001 /
b1001 0
b1010 "
b1010 -
b1010 :
1)
#70000
0)
#75000
b1000 /
b1000 0
b1001 "
b1001 -
b1001 :
1)
#80000
0)
#85000
b111 /
b111 0
b1000 "
b1000 -
b1000 :
1)
#90000
0)
#95000
b110 /
b110 0
b111 "
b111 -
b111 :
1)
#100000
0)
#105000
b101 /
b101 0
b110 "
b110 -
b110 :
1)
#110000
0)
#115000
b100 /
b100 0
b101 "
b101 -
b101 :
1)
#120000
0)
#125000
b11 /
b11 0
b100 "
b100 -
b100 :
1)
#130000
0)
#135000
b10 /
b10 0
b11 "
b11 -
b11 :
1)
#140000
0)
#145000
b1 /
b1 0
b10 "
b10 -
b10 :
1)
#150000
0)
#155000
b0 /
b0 0
b1 "
b1 -
b1 :
1)
#160000
0)
#165000
1!
11
b0 "
b0 -
b0 :
b10 /
b10 +
b10 .
1)
#170000
0)
#175000
b1 0
0!
01
b10 "
b10 -
b10 :
b1 /
1)
b0 +
b0 .
#180000
0)
#185000
b0 0
b1 "
b1 -
b1 :
b10001 /
b100 +
b100 .
1)
#190000
0)
#195000
b10000 0
b10001 "
b10001 -
b10001 :
b10000 /
1)
b0 +
b0 .
#200000
0)
#205000
b1111 /
b1111 0
b10000 "
b10000 -
b10000 :
1)
#210000
0)
#215000
b1110 /
b1110 0
b1111 "
b1111 -
b1111 :
1)
#220000
0)
#225000
b1101 /
b1101 0
b1110 "
b1110 -
b1110 :
1)
#230000
0)
#235000
b1100 /
b1100 0
b1101 "
b1101 -
b1101 :
1)
#240000
0)
#245000
b1011 /
b1011 0
b1100 "
b1100 -
b1100 :
1)
#250000
0)
#255000
b1010 /
b1010 0
b1011 "
b1011 -
b1011 :
1)
#260000
0)
#265000
b1001 /
b1001 0
b1010 "
b1010 -
b1010 :
1)
#270000
0)
#275000
b1000 /
b1000 0
b1001 "
b1001 -
b1001 :
1)
#280000
0)
#285000
b111 /
b111 0
b1000 "
b1000 -
b1000 :
1)
#290000
0)
#295000
b110 /
b110 0
b111 "
b111 -
b111 :
1)
#300000
0)
#305000
b101 /
b101 0
b110 "
b110 -
b110 :
1)
#310000
0)
#315000
b100 /
b100 0
b101 "
b101 -
b101 :
1)
#320000
0)
#325000
b11 /
b11 0
b100 "
b100 -
b100 :
1)
#330000
0)
#335000
b10 /
b10 0
b11 "
b11 -
b11 :
1)
#340000
0)
#345000
b1 /
b1 0
b10 "
b10 -
b10 :
1)
#350000
0)
#355000
b10 /
0*
1)
