Counter/counter.v
module counter #(
    parameter pGREEN_INIT_VAL = 14,
    parameter pYELLOW_INIT_VAL = 2,
    parameter pRED_INIT_VAL = 17,
    parameter pCNT_WIDTH = 5,
    parameter pINIT_WIDTH = 3
)(
    input wire clk,
    input wire rst_n,
    input wire en,
    input wire [pINIT_WIDTH-1:0] init,
    output wire last,
    output wire [pCNT_WIDTH-1:0] count_out
);

    localparam pGREEN_IDX = 0;
    localparam pYELLOW_IDX = 1;
    localparam pRED_IDX = 2;

    reg [pCNT_WIDTH-1:0] count;
    wire [pCNT_WIDTH-1:0] next_count;
    wire [pCNT_WIDTH-1:0] dec_value;

    assign dec_value = count + 5'b11111;

    assign next_count = !rst_n              ? pGREEN_INIT_VAL :
                        init[pGREEN_IDX]    ? pGREEN_INIT_VAL   :
                        init[pYELLOW_IDX]   ? pYELLOW_INIT_VAL  :
                        init[pRED_IDX]      ? pRED_INIT_VAL     : 
                        en                  ? dec_value         : 1;


    // thanh ghi
    always @(posedge clk or negedge rst_n) begin
        if(!rst_n) begin
            count <= 0;
        end else if (en) begin 
            count <= next_count;
        end else begin
            count <= 0; // giữ nguyên giá trị
        end
    end

    // comparator
    assign last = (count == 4'b0) ? 1'b1 : 1'b0;
    assign count_out = count;

endmodule
//   // Counter logic goes here


// // Cho đèn sáng theo thứ tự: xanh, vàng, đỏ
// // Đếm từ 14->0->2->17->0->14
// module counter #(
//     parameter pGREEN_INIT_VAL = 14,
//     parameter pYELLOW_INIT_VAL = 2,
//     parameter pRED_INIT_VAL = 17,
//     parameter pCNT_WIDTH = 5, // log2(pRED_INIT_VAL+1)
//     parameter pINIT_WIDTH = 3
// )(
//     input wire clk,
//     input wire en,
//     input wire rst_n,
//     input wire [pINIT_WIDTH-1:0] init,
//     output wire last,
//     output wire [pCNT_WIDTH-1:0] count_out
// );
    
    
//     parameter pGREEN_IDX = 0;
//     parameter pYELLOW_IDX = 1;
//     parameter pRED_IDX = 2;
    
    
//     reg [pCNT_WIDTH-1:0] count;
    
    
//     always @(posedge clk or negedge rst_n) begin
//         if (!rst_n) begin
//             count <= pGREEN_INIT_VAL;
//         end
//         else if (init[pGREEN_IDX]) begin
//             count <= pGREEN_INIT_VAL;
//         end
//         else if (init[pYELLOW_IDX]) begin
//             count <= pYELLOW_INIT_VAL;
//         end
//         else if (init[pRED_IDX]) begin
//             count <= pRED_INIT_VAL;
//         end
//         else if (en) begin
//             count <= count - 1;
//         end
//     end
    
   
//     assign last = (count == 0) ? 1'b1 : 1'b0;
//     assign count_out = count;

// endmodule
`timescale 1ns/1ps
module counter_tb;

    // Parameters
    parameter pGREEN_INIT_VAL  = 14;
    parameter pYELLOW_INIT_VAL = 2;
    parameter pRED_INIT_VAL    = 17;
    parameter pCNT_WIDTH       = 5; // log2(pRED_INIT_VAL+1)
    parameter pINIT_WIDTH      = 3;
    parameter CLK_PERIOD       = 10;

    // Signals
    reg clk;
    reg rst_n;
    reg en;
    reg [pINIT_WIDTH-1:0] init;
    wire last;
    wire [pCNT_WIDTH-1:0] count_out;

    // Instantiate DUT
    counter #(
        .pGREEN_INIT_VAL(pGREEN_INIT_VAL),
        .pYELLOW_INIT_VAL(pYELLOW_INIT_VAL),
        .pRED_INIT_VAL(pRED_INIT_VAL),
        .pCNT_WIDTH(pCNT_WIDTH),
        .pINIT_WIDTH(pINIT_WIDTH)
    ) uut (
        .clk(clk),
        .en(en),
        .rst_n(rst_n),
        .init(init),
        .last(last),
        .count_out(count_out)
    );

    // Clock generator
    always #(CLK_PERIOD/2) clk = ~clk;

    // VCD
    initial begin
        $dumpfile("counter_tb.vcd");
        $dumpvars(0, counter_tb);
    end

    // Test procedure
    initial begin
        // Initial values
        clk = 0;
        rst_n = 0;
        en = 0;
        init = 3'b000;

        // Reset
        #20;
        rst_n = 1;

        // Start with GREEN
        #10;
        init = 3'b001; // GREEN
        #10;
        init = 3'b000;
        en = 1;

        // Wait until GREEN expires
        wait (last);
        #9.99;
        en = 1;

        // Set YELLOW
        init = 3'b010;
        #10;
        init = 3'b000;
        en = 1;

        // Wait until YELLOW expires
        wait (last);
        #9.99;
        en = 1;

        // Set RED
        init = 3'b100;
        #10;
        init = 3'b000;
        en = 1;

        // Wait until RED expires
        wait (last);
        #9.99;
        en = 1;

        // Back to GREEN
        init = 3'b001;
        #10;
        init = 3'b000;
        en = 1;

        // Run for a bit then finish
        #(20 * CLK_PERIOD);
        $finish;
    end

endmodule

Counter/counter_tb.vcd
$date
	Tue Aug 12 15:00:43 2025
$end
$version
	Icarus Verilog
$end
$timescale
	1ps
$end
$scope module counter_tb $end
$var wire 1 ! last $end
$var wire 5 " count_out [4:0] $end
$var parameter 32 # CLK_PERIOD $end
$var parameter 32 $ pCNT_WIDTH $end
$var parameter 32 % pGREEN_INIT_VAL $end
$var parameter 32 & pINIT_WIDTH $end
$var parameter 32 ' pRED_INIT_VAL $end
$var parameter 32 ( pYELLOW_INIT_VAL $end
$var reg 1 ) clk $end
$var reg 1 * en $end
$var reg 3 + init [2:0] $end
$var reg 1 , rst_n $end
$scope module uut $end
$var wire 1 ) clk $end
$var wire 5 - count_out [4:0] $end
$var wire 1 * en $end
$var wire 3 . init [2:0] $end
$var wire 1 , rst_n $end
$var wire 5 / next_count [4:0] $end
$var wire 1 ! last $end
$var wire 5 0 dec_value [4:0] $end
$var parameter 32 1 pCNT_WIDTH $end
$var parameter 32 2 pGREEN_IDX $end
$var parameter 32 3 pGREEN_INIT_VAL $end
$var parameter 32 4 pINIT_WIDTH $end
$var parameter 32 5 pRED_IDX $end
$var parameter 32 6 pRED_INIT_VAL $end
$var parameter 32 7 pYELLOW_IDX $end
$var parameter 32 8 pYELLOW_INIT_VAL $end
$var reg 5 9 count [4:0] $end
$upscope $end
$upscope $end
$enddefinitions $end
$comment Show the parameter values. $end
$dumpall
b10 8
b1 7
b10001 6
b10 5
b11 4
b1110 3
b0 2
b101 1
b10 (
b10001 '
b11 &
b1110 %
b101 $
b1010 #
$end
#0
$dumpvars
b0 9
b11111 0
b1110 /
b0 .
b0 -
0,
b0 +
0*
0)
b0 "
1!
$end
#5000
1)
#10000
0)
#15000
1)
#20000
b1 /
0)
1,
#25000
1)
#30000
b1110 /
0)
b1 +
b1 .
#35000
1)
#40000
b11111 /
0)
1*
b0 +
b0 .
#45000
b11110 /
0!
b11110 0
b11111 "
b11111 -
b11111 9
1)
#49990
b10 /
b10 +
b10 .
#50000
0)
#55000
b1 0
b10 "
b10 -
b10 9
1)
#59990
b1 /
b0 +
b0 .
#60000
0)
#65000
b0 /
b0 0
b1 "
b1 -
b1 9
1)
#70000
0)
#75000
b11111 /
1!
b11111 0
b0 "
b0 -
b0 9
1)
#80000
0)
#84990
b10001 /
b100 +
b100 .
#85000
0!
b10000 0
b10001 "
b10001 -
b10001 9
1)
#90000
0)
#94990
b10000 /
b0 +
b0 .
#95000
b1111 /
b1111 0
b10000 "
b10000 -
b10000 9
1)
#100000
0)
#105000
b1110 /
b1110 0
b1111 "
b1111 -
b1111 9
1)
#110000
0)
#115000
b1101 /
b1101 0
b1110 "
b1110 -
b1110 9
1)
#120000
0)
#125000
b1100 /
b1100 0
b1101 "
b1101 -
b1101 9
1)
#130000
0)
#135000
b1011 /
b1011 0
b1100 "
b1100 -
b1100 9
1)
#140000
0)
#145000
b1010 /
b1010 0
b1011 "
b1011 -
b1011 9
1)
#150000
0)
#155000
b1001 /
b1001 0
b1010 "
b1010 -
b1010 9
1)
#160000
0)
#165000
b1000 /
b1000 0
b1001 "
b1001 -
b1001 9
1)
#170000
0)
#175000
b111 /
b111 0
b1000 "
b1000 -
b1000 9
1)
#180000
0)
#185000
b110 /
b110 0
b111 "
b111 -
b111 9
1)
#190000
0)
#195000
b101 /
b101 0
b110 "
b110 -
b110 9
1)
#200000
0)
#205000
b100 /
b100 0
b101 "
b101 -
b101 9
1)
#210000
0)
#215000
b11 /
b11 0
b100 "
b100 -
b100 9
1)
#220000
0)
#225000
b10 /
b10 0
b11 "
b11 -
b11 9
1)
#230000
0)
#235000
b1 /
b1 0
b10 "
b10 -
b10 9
1)
#240000
0)
#245000
b0 /
b0 0
b1 "
b1 -
b1 9
1)
#250000
0)
#255000
b11111 /
1!
b11111 0
b0 "
b0 -
b0 9
1)
#260000
0)
#264990
b1110 /
b1 +
b1 .
#265000
0!
b1101 0
b1110 "
b1110 -
b1110 9
1)
#270000
0)
#274990
b1101 /
b0 +
b0 .
#275000
b1100 /
b1100 0
b1101 "
b1101 -
b1101 9
1)
#280000
0)
#285000
b1011 /
b1011 0
b1100 "
b1100 -
b1100 9
1)
#290000
0)
#295000
b1010 /
b1010 0
b1011 "
b1011 -
b1011 9
1)
#300000
0)
#305000
b1001 /
b1001 0
b1010 "
b1010 -
b1010 9
1)
#310000
0)
#315000
b1000 /
b1000 0
b1001 "
b1001 -
b1001 9
1)
#320000
0)
#325000
b111 /
b111 0
b1000 "
b1000 -
b1000 9
1)
#330000
0)
#335000
b110 /
b110 0
b111 "
b111 -
b111 9
1)
#340000
0)
#345000
b101 /
b101 0
b110 "
b110 -
b110 9
1)
#350000
0)
#355000
b100 /
b100 0
b101 "
b101 -
b101 9
1)
#360000
0)
#365000
b11 /
b11 0
b100 "
b100 -
b100 9
1)
#370000
0)
#375000
b10 /
b10 0
b11 "
b11 -
b11 9
1)
#380000
0)
#385000
b1 /
b1 0
b10 "
b10 -
b10 9
1)
#390000
0)
#395000
b0 /
b0 0
b1 "
b1 -
b1 9
1)
#400000
0)
#405000
b11111 /
1!
b11111 0
b0 "
b0 -
b0 9
1)
#410000
0)
#415000
b11110 /
0!
b11110 0
b11111 "
b11111 -
b11111 9
1)
#420000
0)
#425000
b11101 /
b11101 0
b11110 "
b11110 -
b11110 9
1)
#430000
0)
#435000
b11100 /
b11100 0
b11101 "
b11101 -
b11101 9
1)
#440000
0)
#445000
b11011 /
b11011 0
b11100 "
b11100 -
b11100 9
1)
#450000
0)
#455000
b11010 /
b11010 0
b11011 "
b11011 -
b11011 9
1)
#460000
0)
#465000
b11001 /
b11001 0
b11010 "
b11010 -
b11010 9
1)
